chloris_app_sdk/__init__.py
chloris_app_sdk/client.py
chloris_app_sdk/utils.py
chloris_app_sdk-1.2.0.dist-info/licenses/LICENSE
chloris_app_sdk-1.2.0.dist-info/METADATA
chloris_app_sdk-1.2.0.dist-info/WHEEL
chloris_app_sdk-1.2.0.dist-info/top_level.txt
chloris_app_sdk-1.2.0.dist-info/RECORD
