Metadata-Version: 2.4
Name: chloris_app_sdk
Version: 1.2.0
Summary: A package created with a setuptools tutorial.  See article link for more details.
Home-page: https://app.chloris.earth/docs/index.html
License: MIT
License-File: LICENSE
Requires-Dist: boto3
Requires-Dist: urllib3
Dynamic: license-file
